README.rst
setup.py
src/AnthraxEplasty.egg-info/PKG-INFO
src/AnthraxEplasty.egg-info/SOURCES.txt
src/AnthraxEplasty.egg-info/dependency_links.txt
src/AnthraxEplasty.egg-info/entry_points.txt
src/AnthraxEplasty.egg-info/namespace_packages.txt
src/AnthraxEplasty.egg-info/requires.txt
src/AnthraxEplasty.egg-info/top_level.txt
src/anthrax/__init__.py
src/anthrax/eplasty/__init__.py
src/anthrax/eplasty/field.py
src/anthrax/eplasty/loader.py
src/anthrax/eplasty/reflector.py