Metadata-Version: 1.1
Name: AnthraxEplasty
Version: 0.0.3
Summary: Anthrax - generating forms from Elephantoplasty objects
Home-page: http://github.com/zefciu/Anthrax
Author: Szymon Pyżalski
Author-email: zefciu <szymon@pythonista.net>
License: UNKNOWN
Keywords: form web orm database
Platform: UNKNOWN
Classifier: Development Status :: 1 - Planning
Classifier: Intended Audience :: Developers
Classifier: License :: OSI Approved :: BSD License
Classifier: Programming Language :: Python :: 3
Classifier: Programming Language :: Python :: 3.2
Classifier: Topic :: Internet :: WWW/HTTP :: Dynamic Content
